<?xml version="1.0" encoding="utf-8"?>
<!-- 被2013 sp1 () 使用XMLSpy v编辑的 (http://www.altova.com) by -->
<!-- edited with XMLSpy v2011 (http://www.altova.com) by 233 (TeaM DJiNN) -->
<!--
type 类型 1主动技能 2被动技能 3协助技能 4属性技能

showFlag  技能栏显示标识
		  1 进攻有球时
		  2 进攻无球时
		  3 防守带球者时
		  4 非对位防守者时
		  5 任意进攻轮时
		  6 任意防守轮时
		  7 任何时候都可


eff 特效动画 加载到球员身上
effIcon 特效头顶图标

rangType 作用范围 暂时不要填 
		1自己 
		2队友 
		3对面球员
		4防守我的球员

useStep  	   可使用步骤
actionType     1传球技能 2射门技能 3传球射门都使用的技能

keepRound  技能效果持续的回合数
			0用完结束
			n持续n回合

trail 动画name 有内容射门带拖尾效果 
keepRound="1" shootSkillID  和PlayerDefine的SkillShoot的ID对应 有内容射门的时候使用此曲线

effFun   功能标识  
		2  射到死角 
		3  射门到门柱
		4  使用推射
		5  超大力抽射
		6  守门员延迟 0.5秒 扑球
		7  出现球员补射
		8  对撞球协助
		9  球员卧草后摄像机焦点到该球员上
		10 彩虹过人
		11 传球定格 跑向接球人的前面
		12 传球/射门后 肘击
		13 增加一个防守球员
		14 射偏
		15 大圣超车

des 技能描述
-->
<Object>
	<Property ID="0" name="传球" type="1" icon="0" des=" "/>
	<Property ID="1" name="射门" type="1" icon="1" des=" "/>
	<Property ID="1001" name="精准推射" type="1" icon="101102" des=" "/>
	<Property ID="1002" name="暴力抽射" type="1" icon="101402" des=" "/>
	<Property ID="1003" name="彩虹过人" type="1" icon="102024" des=" "/>
	<Property ID="1004" name="捡漏达人" type="3" icon="103007" des=" "/>
	<Property ID="1005" name="意识传递" type="1" icon="103007" des=" "/>
	<Property ID="1006" name="手术刀传球" type="1" icon="103007" des=" "/>
	<Property ID="1007" name="魔性庆祝" type="3" icon="103007" des=" "/>
	<Property ID="1008" name="全能中场" type="1" icon="103007" des=" "/>
	<Property ID="1009" name="直塞身后" type="3" icon="101402" des=" "/>
	<Property ID="1010" name="大圣超车" type="1" icon="101402" des=" "/>
	<Property ID="1011" name="精准抢断" type="1" icon="101402" des=" "/>
	<Property ID="1012" name="外脚背助攻" type="1" icon="101402" des=" "/>
	<Property ID="1013" name="坚定信心" type="3" icon="101402" des=" "/>
	<Property ID="1014" name="卧草战术" type="3" icon="101402" des="  "/>
	<Property ID="1015" name="越位陷阱" type="3" icon="101102" des=" "/>
	<Property ID="1016" name="暴力抢断" type="1" icon="101102" des=" "/>
	<Property ID="1017" name="后防中坚" type="3" icon="101102" des=" "/>
	<Property ID="1018" name="断球反击" type="3" icon="101102" des=" "/>
	<Property ID="1019" name="凶狠铲球" type="1" icon="101102" des=" "/>
	<Property ID="1020" name="透支防守" type="1" icon="101102" des=" "/>
	<Property ID="1021" name="出击狂魔" type="1" icon="101102" des=" "/>
	<Property ID="1022" name="大力轰门" type="1" icon="101102" des=" "/>
	<Property ID="1023" name="机敏跑位" type="1" icon="101102" des=" "/>
	<Property ID="1024" name="人球分过" type="1" icon="101102" des=" "/>
	<Property ID="1025" name="兰花指突破" type="1" icon="101102" des=" "/>
	<Property ID="1026" name="金童状态" type="1" icon="101102" des=" "/>
	<Property ID="1027" name="远程发炮" type="1" icon="101102" des=" "/>
	<Property ID="1028" name="王牌杀手" type="1" icon="101102" des=" "/>
	<Property ID="1029" name="进球鼓舞" type="3" icon="101102" des=" "/>
	<Property ID="1030" name="精妙传递" type="1" icon="101102" des=" "/>
	<Property ID="1031" name="协防补位" type="3" icon="101102" des=" "/>
	<Property ID="1032" name="撞墙配合" type="3" icon="101102" des=" "/>
	<Property ID="1033" name="精准抢断" type="1" icon="101102" des=" "/>
	<Property ID="1034" name="振臂高呼" type="3" icon="101102" des=" "/>
	<Property ID="1035" name="战术犯规" type="3" icon="101102" des=" "/>
	<Property ID="1036" name="门柱保命" type="1" icon="101102" des=" "/>
	<Property ID="1037" name="霸气补球" type="1" icon="101102" des=" "/>
	<Property ID="1038" name="泪流满面" type="3" icon="101102" des=" "/>
	<Property ID="1039" name="劲射" type="1" icon="101102" des=" "/>
	<Property ID="1040" name="精神领袖" type="3" icon="101102" des=" "/>
	<Property ID="1041" name="变相突破" type="1" icon="101102" des=" "/>
	<Property ID="1042" name="留洋快马" type="1" icon="101102" des=" "/>
	<Property ID="1043" name="精准传递" type="1" icon="101102" des=" "/>
	<Property ID="1044" name="中场支柱" type="3" icon="101102" des=" "/>
	<Property ID="1045" name="抢断大师" type="3" icon="101102" des=" "/>
	<Property ID="1046" name="偷听战术" type="1" icon="101102" des=" "/>
	<Property ID="1047" name="精准选位" type="3" icon="101102" des=" "/>
	<Property ID="1048" name="拦截大师" type="3" icon="101102" des=" "/>
	<Property ID="1049" name="贴身防守" type="1" icon="101102" des=" "/>
	<Property ID="1050" name="飞身救险" type="1" icon="101102" des=" "/>
	<Property ID="1051" name="妙传" type="1" icon="101102" des=" "/>
	<Property ID="1052" name="滑铲" type="1" icon="101102" des=" "/>
	<Property ID="1053" name="劲射" type="1" icon="101102" des=" "/>
	<Property ID="1054" name="扣球过人" type="1" icon="101102" des=" "/>
	<Property ID="1055" name="奋力扑救" type="1" icon="101102" des=" "/>
	<Property ID="1056" name="扑救" type="1" icon="101102" des=" "/>
	<Property ID="1057" name="卡位" type="1" icon="101102" des=" "/>
	<Property ID="1058" name="趟球过人" type="1" icon="101102" des=" "/>
	<Property ID="2101" name="穿裆射门" type="1" icon="101102" des=" "/>
	<Property ID="2102" name="单车过人" type="1" icon="101102" des=" "/>
	<Property ID="2103" name="嗜血倒钩" type="1" icon="101102" des=" "/>
	<Property ID="2201" name="大力出奇迹" type="1" icon="101102" des=" "/>
	<Property ID="2202" name="马赛回旋" type="1" icon="101102" des=" "/>
	<Property ID="2203" name="中场屏障" type="1" icon="101102" des=" "/>
	<Property ID="2301" name="高位压迫" type="1" icon="101102" des=" "/>
	<Property ID="2302" name="嘲讽式防守" type="1" icon="101102" des=" "/>
	<Property ID="2303" name="防线指挥官" type="1" icon="101102" des=" "/>
	<Property ID="3001" name="大师级射门" type="4" icon="101102"/>
	<Property ID="3002" name="大师级传球" type="4" icon="101102"/>
	<Property ID="3003" name="大师级盘带" type="4" icon="101102"/>
	<Property ID="3004" name="大师级防守" type="4" icon="101102"/>
	<Property ID="3005" name="大师级拦截" type="4" icon="101102"/>
	<Property ID="3006" name="大师级抢断" type="4" icon="101102"/>
	<Property ID="3007" name="大师级控球" type="4" icon="101102"/>
	<Property ID="3008" name="大师级守门" type="4" icon="101102"/>
	<Property ID="3009" name="精英级射门" type="4" icon="101102"/>
	<Property ID="3010" name="精英级传球" type="4" icon="101102"/>
	<Property ID="3011" name="精英级盘带" type="4" icon="101102"/>
	<Property ID="3012" name="精英级防守" type="4" icon="101102"/>
	<Property ID="3013" name="精英级拦截" type="4" icon="101102"/>
	<Property ID="3014" name="精英级抢断" type="4" icon="101102"/>
	<Property ID="3015" name="精英级控球" type="4" icon="101102"/>
	<Property ID="3016" name="精英级守门" type="4" icon="101102"/>
</Object>
